ASAPPpy/__init__.py
ASAPPpy/agents.py
ASAPPpy/amaia_v3.0.py
ASAPPpy/chatbot.py
ASAPPpy/downloader.py
ASAPPpy/feature_extraction.py
ASAPPpy/load_embeddings.py
ASAPPpy/sts_model.py
ASAPPpy/agents/__init__.py
ASAPPpy/agents/_base.py
ASAPPpy/classifiers/__init__.py
ASAPPpy/classifiers/svm.py
ASAPPpy/classifiers/svm_binaria.py
ASAPPpy/classifiers/svm_restantes_classes.py
ASAPPpy/classifiers/trained_models/.DS_Store
ASAPPpy/classifiers/trained_models/svm_binary_170121.pickle
ASAPPpy/classifiers/trained_models/svm_multiclass_020121.pickle
ASAPPpy/classifiers/vectors/.DS_Store
ASAPPpy/classifiers/vectors/vect_binary_170121
ASAPPpy/classifiers/vectors/vect_multiclass_020121
ASAPPpy/datasets/AIA-BDE_v2.0.txt
ASAPPpy/datasets/divididossopcomlegendas.txt
ASAPPpy/feature_engineering/__init__.py
ASAPPpy/feature_engineering/lexical_features.py
ASAPPpy/feature_engineering/semantic_features.py
ASAPPpy/feature_engineering/syntactic_features.py
ASAPPpy/feature_selection/__init__.py
ASAPPpy/feature_selection/feature_selection.py
ASAPPpy/indexers/__init__.py
ASAPPpy/indexers/PyLucene/__init__.py
ASAPPpy/indexers/PyLucene/pylucene.py
ASAPPpy/indexers/Whoosh/__init__.py
ASAPPpy/indexers/Whoosh/whoosh_create_index.py
ASAPPpy/indexers/Whoosh/whoosh_make_query.py
ASAPPpy/indexers/Whoosh/indexes/FAQs_no_analyser_AIA-BDE_v2.0/MAIN_WRITELOCK
ASAPPpy/indexers/Whoosh/indexes/FAQs_no_analyser_AIA-BDE_v2.0/MAIN_m910yey531vtvlrz.seg
ASAPPpy/indexers/Whoosh/indexes/FAQs_no_analyser_AIA-BDE_v2.0/_MAIN_1.toc
ASAPPpy/indexers/Whoosh/indexes/cobaia_chitchat_v1.5/MAIN_WRITELOCK
ASAPPpy/indexers/Whoosh/indexes/cobaia_chitchat_v1.5/MAIN_tra9xg0ci1myadey.seg
ASAPPpy/indexers/Whoosh/indexes/cobaia_chitchat_v1.5/_MAIN_1.toc
ASAPPpy/models/__init__.py
ASAPPpy/models/fastText/__init__.py
ASAPPpy/models/fastText/fasttext.py
ASAPPpy/models/glove/__init__.py
ASAPPpy/models/numberbatch/__init__.py
ASAPPpy/models/ontoPT/__init__.py
ASAPPpy/models/ontoPT/ptlkb.py
ASAPPpy/models/word2vec/__init__.py
ASAPPpy-0.2b1.dist-info/LICENSE
ASAPPpy-0.2b1.dist-info/METADATA
ASAPPpy-0.2b1.dist-info/WHEEL
ASAPPpy-0.2b1.dist-info/top_level.txt
ASAPPpy-0.2b1.dist-info/RECORD
