Metadata-Version: 2.1
Name: ASAPPpy
Version: 0.2b1
Summary: Semantic Textual Similarity and Dialogue System package for Python
Home-page: UNKNOWN
Author: José Santos
Author-email: santos@student.dei.uc.pt
License: MIT License
Project-URL: Source Code, https://github.com/NLP-CISUC/ASAPPpy
Keywords: Natural Language Processing,NLP,Sentence Similarity,Semantic Textual Similarity,STS,Dialogue Agents,Chatbot Framework,Chatbot
Platform: any
Classifier: Development Status :: 3 - Alpha
Classifier: Environment :: Console
Classifier: Intended Audience :: Science/Research
Classifier: License :: OSI Approved :: MIT License
Classifier: Operating System :: OS Independent
Classifier: Programming Language :: Python :: 3.6
Classifier: Programming Language :: Python :: 3 :: Only
Classifier: Topic :: Scientific/Engineering :: Artificial Intelligence
Classifier: Topic :: Scientific/Engineering :: Information Analysis
Classifier: Topic :: Text Processing :: Linguistic
Requires-Python: >=3.6.1
Requires-Dist: setuptools (==49.6.0)
Requires-Dist: imbalanced-learn (==0.7.0)
Requires-Dist: scikit-learn (>=0.22.2)
Requires-Dist: pandas (>=1.1.1)
Requires-Dist: requests
Requires-Dist: slackclient (==2.1.0)
Requires-Dist: slackeventsapi (==2.1.0)
Requires-Dist: nltk (==3.4.5)
Requires-Dist: NLPyPort (==2.2.5)
Requires-Dist: spacy
Requires-Dist: gensim
Requires-Dist: joblib
Requires-Dist: num2words
Requires-Dist: Whoosh
Requires-Dist: Keras
Requires-Dist: tensorflow
Requires-Dist: cufflinks
Requires-Dist: matplotlib
Requires-Dist: seaborn
